DensityTrace/__init__.py
DensityTrace/main.py
DensityTrace-0.1.0.dist-info/DESCRIPTION.rst
DensityTrace-0.1.0.dist-info/METADATA
DensityTrace-0.1.0.dist-info/RECORD
DensityTrace-0.1.0.dist-info/WHEEL
DensityTrace-0.1.0.dist-info/metadata.json
DensityTrace-0.1.0.dist-info/top_level.txt
