Metadata-Version: 2.0
Name: DensityTrace
Version: 0.1.0
Summary: DensityTrace
Home-page: https://github.com/yuhangwang/DensityTrace
Author: Yuhang(Steven) Wang
Author-email: UNKNOWN
License: MIT/X11
Requires-Dist: numpy
Requires-Dist: typing
